yummyanime/__init__.py
yummyanime/api.py
yummyanime/enums.py
yummyanime/exceptions.py
yummyanime/parsers/__init__.py
yummyanime/parsers/abstract_parser.py
yummyanime/parsers/utils.py
yummyanime/parsers/kodik/__init__.py
yummyanime/parsers/kodik/downloader.py
yummyanime/routes/__init__.py
yummyanime/routes/_abs.py
yummyanime/routes/anime.py
yummyanime/routes/reviews.py
yummyanime/routes/trailers.py
yummyanime/routes/users.py
yummyanime/structs/__init__.py
yummyanime/structs/_base.py
yummyanime/structs/_enums.py
yummyanime/structs/anime.py
yummyanime/structs/anime_genres.py
yummyanime/structs/blogger.py
yummyanime/structs/feed.py
yummyanime/structs/likes.py
yummyanime/structs/post.py
yummyanime/structs/review.py
yummyanime/structs/trailers.py
yummyanime/structs/user.py
yummyanime/structs/video.py
yummyanime-0.0.9.dist-info/LICENSE
yummyanime-0.0.9.dist-info/METADATA
yummyanime-0.0.9.dist-info/WHEEL
yummyanime-0.0.9.dist-info/top_level.txt
yummyanime-0.0.9.dist-info/RECORD
