Metadata-Version: 2.1
Name: yummyanime
Version: 0.0.9
Summary: Yummy Anime API wrapper
Author-email: "IM.Corp" <root@yummyani.me>
Project-URL: Homepage, https://yummyani.me/
Classifier: Programming Language :: Python :: 3
Classifier: License :: OSI Approved :: MIT License
Classifier: Operating System :: OS Independent
Requires-Python: >=3.9
License-File: LICENSE
Requires-Dist: aiohttp~=3.9.5
Requires-Dist: json5~=0.9.25
Requires-Dist: beautifulsoup4~=4.12.3
